binary_packer/__init__.py
binary_packer/factory.py
binary_packer/fields_structs.py
binary_packer/packer.py
binary_packer/types.py
binary_packer-1.0.1.dist-info/METADATA
binary_packer-1.0.1.dist-info/WHEEL
binary_packer-1.0.1.dist-info/top_level.txt
binary_packer-1.0.1.dist-info/RECORD
