Metadata-Version: 2.1
Name: binary-packer
Version: 1.0.1
Summary: Light and fast packer dataclasses to binary
Home-page: https://github.com/moff4/packer
Author: Komissarov Andrey
Author-email: Komissar.off.andrey@gmail.com
Classifier: Programming Language :: Python :: 3.9
Classifier: Programming Language :: Python :: 3.10
Classifier: Programming Language :: Python :: 3.11
Classifier: Operating System :: OS Independent
